odoo/addons/sale_channel_search_engine_product/README.rst
odoo/addons/sale_channel_search_engine_product/__init__.py
odoo/addons/sale_channel_search_engine_product/__manifest__.py
odoo/addons/sale_channel_search_engine_product/i18n/it.po
odoo/addons/sale_channel_search_engine_product/i18n/sale_channel_search_engine_product.pot
odoo/addons/sale_channel_search_engine_product/models/__init__.py
odoo/addons/sale_channel_search_engine_product/models/product_product.py
odoo/addons/sale_channel_search_engine_product/models/product_template.py
odoo/addons/sale_channel_search_engine_product/readme/CONTRIBUTORS.rst
odoo/addons/sale_channel_search_engine_product/readme/DESCRIPTION.rst
odoo/addons/sale_channel_search_engine_product/readme/newsfragments/.gitignore
odoo/addons/sale_channel_search_engine_product/static/description/icon.png
odoo/addons/sale_channel_search_engine_product/static/description/index.html
odoo/addons/sale_channel_search_engine_product/tests/__init__.py
odoo/addons/sale_channel_search_engine_product/tests/test_index_record.py
odoo/addons/sale_channel_search_engine_product/tests/fixtures/12.bugfix
odoo/addons/sale_channel_search_engine_product/tests/fixtures/ir_exports_test.xml
odoo/addons/sale_channel_search_engine_product/views/product_template_view.xml
odoo_addon_sale_channel_search_engine_product-16.0.0.1.1.dist-info/METADATA
odoo_addon_sale_channel_search_engine_product-16.0.0.1.1.dist-info/WHEEL
odoo_addon_sale_channel_search_engine_product-16.0.0.1.1.dist-info/top_level.txt
odoo_addon_sale_channel_search_engine_product-16.0.0.1.1.dist-info/RECORD
